confluent_pyflink/__init__.py
confluent_pyflink/context/__init__.py
confluent_pyflink/context/confluent_context.py
confluent_pyflink/context/context.py
confluent_pyflink/context/java_gateway_manager.py
confluent_pyflink/context/local_context.py
confluent_pyflink/table/__init__.py
confluent_pyflink/table/catalog.py
confluent_pyflink/table/changelog_mode.py
confluent_pyflink/table/data_view.py
confluent_pyflink/table/descriptors.py
confluent_pyflink/table/environment_settings.py
confluent_pyflink/table/explain_detail.py
confluent_pyflink/table/expression.py
confluent_pyflink/table/expressions.py
confluent_pyflink/table/functions.py
confluent_pyflink/table/module.py
confluent_pyflink/table/result_kind.py
confluent_pyflink/table/schema.py
confluent_pyflink/table/serializers.py
confluent_pyflink/table/sql_dialect.py
confluent_pyflink/table/statement_set.py
confluent_pyflink/table/table.py
confluent_pyflink/table/table_config.py
confluent_pyflink/table/table_descriptor.py
confluent_pyflink/table/table_environment.py
confluent_pyflink/table/table_result.py
confluent_pyflink/table/table_schema.py
confluent_pyflink/table/types.py
confluent_pyflink/table/udf.py
confluent_pyflink/table/window.py
confluent_pyflink/table/utils/__init__.py
confluent_pyflink/table/utils/confluent_settings.py
confluent_pyflink/table/utils/confluent_tools.py
confluent_pyflink-1.0.dev1.dist-info/METADATA
confluent_pyflink-1.0.dev1.dist-info/WHEEL
confluent_pyflink-1.0.dev1.dist-info/top_level.txt
confluent_pyflink-1.0.dev1.dist-info/RECORD
