Metadata-Version: 2.4
Name: confluent-pyflink
Version: 1.0.dev1
Summary: Confluent Apache Flink Table API Python
Author-email: Confluent <dev@confluent.io>
License-Expression: Apache-2.0
Project-URL: Homepage, https://confluent.io
Project-URL: Examples, https://github.com/confluentinc/flink-table-api-python-examples
Classifier: Development Status :: 4 - Beta
Classifier: Programming Language :: Python :: 3.9
Classifier: Programming Language :: Python :: 3.10
Classifier: Programming Language :: Python :: 3.11
Classifier: Programming Language :: Python :: 3.12
Requires-Python: >=3.9
Requires-Dist: apache-flink~=2.1.0
Requires-Dist: pydantic-settings>=2.10.1
Requires-Dist: pyyaml
Requires-Dist: confluent-flink-jars==2.1.dev1
